{"guide_commands.md":"6SigqofQ","guide_completion.md":"bZPofBCY","guide_config.md":"CBEFHxzv","guide_extending.md":"2e0sEXLB","guide_flags.md":"CjFyNmcb","guide_getting-started.md":"DNJh3WRP","guide_index.md":"ph7IiA_l","guide_templates.md":"CGAXQJCY","index.md":"Cftxns9Q","reference_api.md":"C-TXW_Hr","reference_compat.md":"B7Im-daE","reference_examples.md":"CrEdR3jG","reference_index.md":"DfAv-IFQ","zh_guide_commands.md":"DxJJU0fS","zh_guide_completion.md":"Dk2Y0XRK","zh_guide_config.md":"Bj-VDFIa","zh_guide_extending.md":"C1s-FBfJ","zh_guide_flags.md":"BEwIci6_","zh_guide_getting-started.md":"aKaBSKU-","zh_guide_index.md":"O8RttGFi","zh_guide_templates.md":"BTLk7Ap1","zh_index.md":"Dwb-a5Yr","zh_reference_api.md":"DPDPmFwz","zh_reference_compat.md":"B0ckSa9s","zh_reference_examples.md":"DWN6iI7A","zh_reference_index.md":"BhKhHSup"}
